retryp
