Metadata-Version: 1.1
Name: retryp
Version: 0.3
Summary: Well-featured retry decorator
Home-page: https://github.com/clearclaw/retryp
Author: J C Lawrence
Author-email: claw@kanga.nu
License: LGPL v3.0
Keywords: decorator exception retry retrying
Platform: UNKNOWN
Classifier: Development Status :: 4 - Beta
Classifier: Intended Audience :: Developers
Classifier: License :: OSI Approved :: GNU Lesser General Public License v3 or later (LGPLv3+)
Classifier: Topic :: Utilities
